backstage_simple_client/__init__.py
backstage_simple_client/client.py
backstage_simple_client/common.py
backstage_simple_client/filters.py
backstage_simple_client/models/entities.py
backstage_simple_client/models/requests.py
backstage_simple_client/models/responses.py
backstage_simple_client-0.1.4.dist-info/LICENSE
backstage_simple_client-0.1.4.dist-info/METADATA
backstage_simple_client-0.1.4.dist-info/WHEEL
backstage_simple_client-0.1.4.dist-info/RECORD
