Metadata-Version: 2.3
Name: backstage-simple-client
Version: 0.1.4
Summary: A simple client for Backstage developer portal
License: MIT
Author: Tomasz Habiger
Author-email: tomasz.habiger@gmail.com
Requires-Python: >=3.11
Classifier: License :: OSI Approved :: MIT License
Classifier: Programming Language :: Python :: 3
Classifier: Programming Language :: Python :: 3.11
Classifier: Programming Language :: Python :: 3.12
Classifier: Programming Language :: Python :: 3.13
Requires-Dist: httpx (>=0.18.2)
Requires-Dist: pydantic (>=1.8.2)
Project-URL: Homepage, https://github.com/thabiger/backstage-simple-client
